pyfracval/__init__.py
pyfracval/app.py
pyfracval/cca_agg.py
pyfracval/cli.py
pyfracval/config.py
pyfracval/logs.py
pyfracval/main_runner.py
pyfracval/particle_generation.py
pyfracval/pca_agg.py
pyfracval/pca_subclusters.py
pyfracval/schemas.py
pyfracval/utils.py
pyfracval/visualization.py
pyfracval-0.1.0.dist-info/METADATA
pyfracval-0.1.0.dist-info/WHEEL
pyfracval-0.1.0.dist-info/entry_points.txt
pyfracval-0.1.0.dist-info/licenses/LICENSE
pyfracval-0.1.0.dist-info/RECORD
