Metadata-Version: 2.4
Name: PyFracVAL
Version: 0.1.0
Summary: Python implementation of FracVAL for generting fractal particle clusters
Author: aetherspritee
Author-email: Mirza Arnaut <mirza.arnaut@tu-dortmund.de>
License-File: LICENSE
Requires-Python: <3.13,>=3.10
Requires-Dist: click>=8.1.7
Requires-Dist: numba>=0.60.0
Requires-Dist: numpy>=1.26.4
Requires-Dist: pandas>=2.2.3
Requires-Dist: polars>=1.12.0
Requires-Dist: pydantic>=2.11.1
Requires-Dist: pyvista>=0.44.1
Requires-Dist: pyyaml>=6.0.2
Requires-Dist: scipy>=1.14.1
Requires-Dist: stpyvista>=0.1.4
Requires-Dist: streamlit>=1.41.1
Requires-Dist: tqdm>=4.66.5
